jon/__init__.py
jon/jon_wrapper.py
javascript_object_notation-0.1.1.dist-info/LICENSE
javascript_object_notation-0.1.1.dist-info/METADATA
javascript_object_notation-0.1.1.dist-info/WHEEL
javascript_object_notation-0.1.1.dist-info/top_level.txt
javascript_object_notation-0.1.1.dist-info/RECORD
