Metadata-Version: 2.1
Name: javascript-object-notation
Version: 0.1.1
Summary: Javascript Object Notation (JON) to access JSON and YAML data.
Home-page: https://github.com/Emmerson-Miranda/javascript-object-notation
Author: Emmerson Miranda
License: MIT
License-File: LICENSE
